pkgcheck/__init__.py
pkgcheck/__main__.py
pkgcheck/_const.py
pkgcheck/_objects.py
pkgcheck/_verinfo.py
pkgcheck/api.py
pkgcheck/base.py
pkgcheck/cli.py
pkgcheck/const.py
pkgcheck/feeds.py
pkgcheck/log.py
pkgcheck/objects.py
pkgcheck/packages.py
pkgcheck/pipeline.py
pkgcheck/reporters.py
pkgcheck/results.py
pkgcheck/runners.py
pkgcheck/sources.py
pkgcheck/utils.py
pkgcheck/addons/__init__.py
pkgcheck/addons/caches.py
pkgcheck/addons/eclass.py
pkgcheck/addons/git.py
pkgcheck/addons/net.py
pkgcheck/addons/profiles.py
pkgcheck/bash/__init__.py
pkgcheck/checks/__init__.py
pkgcheck/checks/acct.py
pkgcheck/checks/cleanup.py
pkgcheck/checks/codingstyle.py
pkgcheck/checks/dropped_keywords.py
pkgcheck/checks/eclass.py
pkgcheck/checks/git.py
pkgcheck/checks/glsa.py
pkgcheck/checks/header.py
pkgcheck/checks/imlate.py
pkgcheck/checks/metadata.py
pkgcheck/checks/metadata_xml.py
pkgcheck/checks/network.py
pkgcheck/checks/overlays.py
pkgcheck/checks/perl.py
pkgcheck/checks/pkgdir.py
pkgcheck/checks/profiles.py
pkgcheck/checks/python.py
pkgcheck/checks/repo.py
pkgcheck/checks/repo_metadata.py
pkgcheck/checks/reserved.py
pkgcheck/checks/ruby.py
pkgcheck/checks/rust.py
pkgcheck/checks/stablereq.py
pkgcheck/checks/unstable_only.py
pkgcheck/checks/visibility.py
pkgcheck/checks/whitespace.py
pkgcheck/scripts/__init__.py
pkgcheck/scripts/argparse_actions.py
pkgcheck/scripts/argparsers.py
pkgcheck/scripts/pkgcheck.py
pkgcheck/scripts/pkgcheck_cache.py
pkgcheck/scripts/pkgcheck_ci.py
pkgcheck/scripts/pkgcheck_replay.py
pkgcheck/scripts/pkgcheck_scan.py
pkgcheck/scripts/pkgcheck_show.py
pkgcheck-0.10.37.data/data/share/bash-completion/completions/pkgcheck
pkgcheck-0.10.37.data/data/share/pkgcheck/caches
pkgcheck-0.10.37.data/data/share/pkgcheck/checks
pkgcheck-0.10.37.data/data/share/pkgcheck/ci.py
pkgcheck-0.10.37.data/data/share/pkgcheck/keywords
pkgcheck-0.10.37.data/data/share/pkgcheck/perl-version.pl
pkgcheck-0.10.37.data/data/share/pkgcheck/pkgcheck.conf
pkgcheck-0.10.37.dist-info/entry_points.txt
pkgcheck-0.10.37.dist-info/licenses/LICENSE
pkgcheck-0.10.37.dist-info/WHEEL
pkgcheck-0.10.37.dist-info/METADATA
pkgcheck-0.10.37.dist-info/RECORD
