Metadata-Version: 2.4
Name: pkgcheck
Version: 0.10.37
Summary: pkgcore-based QA utility for ebuild repos
Author: Marien Zwart
Author-email: Michał Górny <mgorny@gentoo.org>, Tim Harder <radhermit@gmail.com>, Brian Harring <ferringb@gmail.com>, Arthur Zamarin <arthurzam@gentoo.org>
Maintainer-email: Arthur Zamarin <arthurzam@gentoo.org>
Requires-Python: ~=3.11
Classifier: License :: OSI Approved :: BSD License
Classifier: Programming Language :: Python :: 3.11
Classifier: Programming Language :: Python :: 3.12
Classifier: Programming Language :: Python :: 3.13
Classifier: Topic :: Software Development :: Quality Assurance
License-File: LICENSE
Requires-Dist: chardet
Requires-Dist: lazy-object-proxy
Requires-Dist: lxml
Requires-Dist: pathspec
Requires-Dist: tree-sitter~=0.25.0
Requires-Dist: tree-sitter-bash~=0.23.1
Requires-Dist: snakeoil~=0.10.11
Requires-Dist: pkgcore~=0.12.30
Requires-Dist: sphinx ; extra == "doc"
Requires-Dist: snakeoil~=0.10.11 ; extra == "doc"
Requires-Dist: requests ; extra == "network"
Requires-Dist: pytest>=6.0 ; extra == "test"
Requires-Dist: pytest-cov ; extra == "test"
Requires-Dist: requests ; extra == "test"
Project-URL: Documentation, https://pkgcore.github.io/pkgcheck/
Project-URL: Homepage, https://github.com/pkgcore/pkgcheck
Project-URL: Source, https://github.com/pkgcore/pkgcheck
Provides-Extra: doc
Provides-Extra: network
Provides-Extra: test
